Corellia
