Metadata-Version: 1.0
Name: Corellia
Version: 0.5.1
Summary: Fast Task Queue Using Redis
Home-page: https://github.com/Tefx/Corellia
Author: Zhu Zhaomeng
Author-email: zhaomeng.zhu@gmail.com
License: UNKNOWN
Platform: UNKNOWN
Classifier: Development Status :: 3 - Alpha
Classifier: Environment :: Console
Classifier: Intended Audience :: Developers
Classifier: License :: OSI Approved :: GNU Library or Lesser General Public License (LGPL)
Classifier: Topic :: Utilities
